soxspipe/.DS_Store
soxspipe/__init__.py
soxspipe/__version__.py
soxspipe/advanced_settings.yaml
soxspipe/cl_utils.py
soxspipe/default_settings.yaml
soxspipe/docstring_test.py
soxspipe/setup.cfg
soxspipe/soxs_default_settings.yaml
soxspipe/test_settings_soxs.yaml
soxspipe/test_settings_soxs_sim.yaml
soxspipe/test_settings_xsh.yaml
soxspipe/utKit.py
soxspipe/xsh_default_settings.yaml
soxspipe/commonutils/.DS_Store
soxspipe/commonutils/__init__.py
soxspipe/commonutils/combiner.py
soxspipe/commonutils/create_dispersion_map.py
soxspipe/commonutils/data_organiser.py
soxspipe/commonutils/detect_continuum.py
soxspipe/commonutils/detect_order_edges.py
soxspipe/commonutils/detector_lookup.py
soxspipe/commonutils/dispersion_map_to_pixel_arrays.py
soxspipe/commonutils/filenamer.py
soxspipe/commonutils/flux_calibration.py
soxspipe/commonutils/getpackagepath.py
soxspipe/commonutils/horne_extraction.py
soxspipe/commonutils/keyword_lookup.py
soxspipe/commonutils/polynomials.py
soxspipe/commonutils/reducer.py
soxspipe/commonutils/response_function.py
soxspipe/commonutils/set_of_files.py
soxspipe/commonutils/subtract_background.py
soxspipe/commonutils/subtract_sky.py
soxspipe/commonutils/toolkit.py
soxspipe/commonutils/uncompress.py
soxspipe/commonutils/__pycache__/horne_extraction.horne_extraction.extract.locals.rebin-466.py312.1.nbc
soxspipe/commonutils/__pycache__/horne_extraction.horne_extraction.extract.locals.rebin-466.py312.2.nbc
soxspipe/commonutils/__pycache__/horne_extraction.horne_extraction.extract.locals.rebin-466.py312.3.nbc
soxspipe/commonutils/__pycache__/horne_extraction.horne_extraction.extract.locals.rebin-466.py312.nbi
soxspipe/recipes/__init__.py
soxspipe/recipes/base_recipe.py
soxspipe/recipes/soxs_disp_solution.py
soxspipe/recipes/soxs_mbias.py
soxspipe/recipes/soxs_mdark.py
soxspipe/recipes/soxs_mflat.py
soxspipe/recipes/soxs_nod.py
soxspipe/recipes/soxs_order_centres.py
soxspipe/recipes/soxs_spatial_solution.py
soxspipe/recipes/soxs_stare.py
soxspipe-0.15.2.dist-info/LICENSE
soxspipe-0.15.2.dist-info/METADATA
soxspipe-0.15.2.dist-info/WHEEL
soxspipe-0.15.2.dist-info/entry_points.txt
soxspipe-0.15.2.dist-info/top_level.txt
soxspipe-0.15.2.dist-info/RECORD
