Metadata-Version: 2.2
Name: soxspipe
Version: 0.15.2
Summary: A python package and command-line tools to The data-reduction pipeline for the SOXS instrument
Home-page: https://github.com/thespacedoctor/soxspipe
Download-URL: https://github.com/thespacedoctor/soxspipe/archive/v0.15.2.zip
Author: David Young
Author-email: davidrobertyoung@gmail.com
License: GPLv3
Keywords: soxs, eso, data, pipeline, spectra
Classifier: Development Status :: 4 - Beta
Classifier: License :: OSI Approved :: GNU General Public License v3 (GPLv3)
Classifier: Programming Language :: Python :: 3.11
Classifier: Topic :: Utilities
License-File: LICENSE
Requires-Dist: pyyaml==6.0.2
Requires-Dist: soxspipe
Requires-Dist: fundamentals==2.7.6
Requires-Dist: astropy==6.1.2
Requires-Dist: ccdproc==2.4.2
Requires-Dist: docopt==0.6.2
Requires-Dist: photutils==1.13.0
Requires-Dist: matplotlib==3.9.2
Requires-Dist: numpy==2.1.0
Requires-Dist: unicodecsv==0.14.1
Requires-Dist: pandas==2.2.2
Requires-Dist: tabulate==0.9.0
Requires-Dist: bottleneck==1.4.0
Requires-Dist: multiprocess==0.70.16
Requires-Dist: specutils==1.16.0
Requires-Dist: humanize==4.11.0
Requires-Dist: line_profiler
Requires-Dist: memory_profiler
Requires-Dist: scikit-learn
Requires-Dist: jinja2
Dynamic: author
Dynamic: author-email
Dynamic: classifier
Dynamic: description
Dynamic: description-content-type
Dynamic: download-url
Dynamic: home-page
Dynamic: keywords
Dynamic: license
Dynamic: requires-dist
Dynamic: summary
